pubnub_python_tools/__about__.py
pubnub_python_tools/__init__.py
pubnub_python_tools/__main__.py
pubnub_python_tools/app/__init__.py
pubnub_python_tools/app/acl_utils.py
pubnub_python_tools/app/device_manager.py
pubnub_python_tools/app/main_app.py
pubnub_python_tools/app/pubnub_config.py
pubnub_python_tools/app/pubnub_handle_disconnects.py
pubnub_python_tools/app/pubnub_here_now_callback.py
pubnub_python_tools/app/pubnub_listener.py
pubnub_python_tools/app/pubnub_manager.py
pubnub_python_tools/app/pubnub_manager_asyncio.py
pubnub_python_tools/app/pubnub_on_request.py
pubnub_python_tools/app/pubnub_publish.py
pubnub_python_tools/cli/__init__.py
pubnub_python_tools/cli/click.py
pubnub_python_tools/cli/v1.py
pubnub_python_tools/cli/v2.py
pubnub_python_tools/click/__init__.py
pubnub_python_tools/click/env/__init__.py
pubnub_python_tools/click/env/run.py
pubnub_python_tools/click/run/__init__.py
pubnub_python_tools/config/__init__.py
pubnub_python_tools/config/device_manager_config.py
pubnub_python_tools/config/http_on_request_on_connect.py
pubnub_python_tools/config/module_config.py
pubnub_python_tools/config/time_config.py
pubnub_python_tools/logger/__init__.py
pubnub_python_tools/logger/logging_config.py
pubnub_python_tools/run/__init__.py
pubnub_python_tools/run/main.py
pubnub_python_tools/services/async_instance.py
pubnub_python_tools-1.1.4.dist-info/METADATA
pubnub_python_tools-1.1.4.dist-info/WHEEL
pubnub_python_tools-1.1.4.dist-info/entry_points.txt
pubnub_python_tools-1.1.4.dist-info/licenses/LICENSE
pubnub_python_tools-1.1.4.dist-info/RECORD
