Metadata-Version: 2.1
Name: pubnub_python_tools
Version: 1.1.4
Summary: Quickly interact with PubNub's Python SDK.
Project-URL: Homepage, https://github.com/sergio-munoz/pubnub-python-tools/
Project-URL: Bug Tracker, https://github.com/sergio-munoz/pubnub-python-tools/issues
Project-URL: Documentation, https://github.com/sergio-munoz/pubnub-python-tools#readme
Project-URL: Issues, https://github.com/sergio-munoz/pubnub-python-tools/issues
Project-URL: Source, https://github.com/sergio-munoz/pubnub-python-tools
Author-email: Sergio Munoz <sergio.munoz@pubnub.com>
License: MIT License
License-File: LICENSE
Classifier: License :: OSI Approved :: MIT License
Classifier: Operating System :: OS Independent
Classifier: Programming Language :: Python
Classifier: Programming Language :: Python :: 3.7
Classifier: Programming Language :: Python :: 3.8
Classifier: Programming Language :: Python :: 3.9
Classifier: Programming Language :: Python :: 3.10
Classifier: Programming Language :: Python :: 3.11
Classifier: Programming Language :: Python :: Implementation :: CPython
Requires-Python: >=3.7
Requires-Dist: click>=8.0.3
Requires-Dist: pubnub>=7.0.0
Requires-Dist: python-dotenv
